README.rst
setup.py
ctrlc/__init__.py
ctrlc/ctrlc.py
ctrlc.egg-info/PKG-INFO
ctrlc.egg-info/SOURCES.txt
ctrlc.egg-info/dependency_links.txt
ctrlc.egg-info/top_level.txt